pynexusic/AssetNode_Class.py
pynexusic/DOCUMENTUM_API.py
pynexusic/MAXIMO_API.py
pynexusic/NEXUSIC_RESTAPI.py
pynexusic/OSIPI_WebAPI.py
pynexusic/__init__.py
pynexusic/_version.py
pynexusic/utils.py
pynexusic/docs/changehistory.html
pynexusic/docs/genindex.html
pynexusic/docs/index.html
pynexusic/docs/intro.html
pynexusic/docs/objects.inv
pynexusic/docs/py-modindex.html
pynexusic/docs/search.html
pynexusic/docs/searchindex.js
pynexusic/docs/DOCUMENTUM_API/documentum_api.html
pynexusic/docs/DOCUMENTUM_API/documentum_class.html
pynexusic/docs/DOCUMENTUM_API/documentum_examples.html
pynexusic/docs/MAXIMO_API/maximo_api.html
pynexusic/docs/MAXIMO_API/maximo_class.html
pynexusic/docs/MAXIMO_API/maximo_examples.html
pynexusic/docs/NEXUSIC_RESTAPI/nexusic_api.html
pynexusic/docs/NEXUSIC_RESTAPI/nexusic_class.html
pynexusic/docs/NEXUSIC_RESTAPI/nexusic_examples.html
pynexusic/docs/OSIPI_WEBAPI/osipi_api.html
pynexusic/docs/OSIPI_WEBAPI/osipi_class.html
pynexusic/docs/OSIPI_WEBAPI/osipi_examples.html
pynexusic/docs/UTILITIES/utils_docs.html
pynexusic/docs/_sources/changehistory.rst.txt
pynexusic/docs/_sources/index.rst.txt
pynexusic/docs/_sources/intro.rst.txt
pynexusic/docs/_sources/DOCUMENTUM_API/documentum_api.rst.txt
pynexusic/docs/_sources/DOCUMENTUM_API/documentum_class.rst.txt
pynexusic/docs/_sources/DOCUMENTUM_API/documentum_examples.rst.txt
pynexusic/docs/_sources/MAXIMO_API/maximo_api.rst.txt
pynexusic/docs/_sources/MAXIMO_API/maximo_class.rst.txt
pynexusic/docs/_sources/MAXIMO_API/maximo_examples.rst.txt
pynexusic/docs/_sources/NEXUSIC_RESTAPI/nexusic_api.rst.txt
pynexusic/docs/_sources/NEXUSIC_RESTAPI/nexusic_class.rst.txt
pynexusic/docs/_sources/NEXUSIC_RESTAPI/nexusic_examples.rst.txt
pynexusic/docs/_sources/OSIPI_WEBAPI/osipi_api.rst.txt
pynexusic/docs/_sources/OSIPI_WEBAPI/osipi_class.rst.txt
pynexusic/docs/_sources/OSIPI_WEBAPI/osipi_examples.rst.txt
pynexusic/docs/_sources/UTILITIES/utils_docs.rst.txt
pynexusic/docs/_static/basic.css
pynexusic-2.5.5.dist-info/LICENSE.txt
pynexusic-2.5.5.dist-info/METADATA
pynexusic-2.5.5.dist-info/WHEEL
pynexusic-2.5.5.dist-info/top_level.txt
pynexusic-2.5.5.dist-info/RECORD
