Metadata-Version: 2.1
Name: pynexusic
Version: 2.5.5
Summary: Python library to communicate with varies systems such as Wood NEXUS IC, Maximo and OSI PI
Home-page: UNKNOWN
Author: Mahmoud Aboelatta
Author-email: mahmoud.aboelatta@woodplc.com
License: UNKNOWN
Keywords: NEXUS IC,REST API
Platform: UNKNOWN
Classifier: Development Status :: 5 - Production/Stable
Classifier: Intended Audience :: Developers
Classifier: Programming Language :: Python :: 3
Classifier: Programming Language :: Python :: 3.7
Classifier: Programming Language :: Python :: 3.8
Classifier: Programming Language :: Python :: 3 :: Only
Requires-Python: >=3.7, <4
Requires-Dist: requests-ntlm
